ssb_libtest2/__init__.py
ssb_libtest2/__main__.py
ssb_libtest2/functions.py
ssb_libtest2/py.typed
ssb_libtest2-0.0.1.dist-info/LICENSE
ssb_libtest2-0.0.1.dist-info/METADATA
ssb_libtest2-0.0.1.dist-info/WHEEL
ssb_libtest2-0.0.1.dist-info/entry_points.txt
ssb_libtest2-0.0.1.dist-info/RECORD
