Metadata-Version: 2.3
Name: ssb-libtest2
Version: 0.0.1
Summary: SSB Libtest2
License: MIT
Author: Ariel Dahlberg Karlsen
Author-email: 54323769+ArielKarlsen@users.noreply.github.com
Maintainer: Statistics Norway, IT-partner Department (703)
Requires-Python: >=3.10,<4.0
Classifier: Development Status :: 4 - Beta
Classifier: License :: OSI Approved :: MIT License
Classifier: Programming Language :: Python :: 3
Classifier: Programming Language :: Python :: 3.10
Classifier: Programming Language :: Python :: 3.11
Classifier: Programming Language :: Python :: 3.12
Classifier: Programming Language :: Python :: 3.13
Requires-Dist: click (>=8.0.1)
Project-URL: Changelog, https://github.com/statisticsnorway/ssb-libtest2/releases
Project-URL: Documentation, https://statisticsnorway.github.io/ssb-libtest2
Project-URL: Homepage, https://github.com/statisticsnorway/ssb-libtest2
Project-URL: Repository, https://github.com/statisticsnorway/ssb-libtest2
